{
    "info": {
        "description": "ISAT",
        "folder": "D:/experiments/Dr_code/zxp_others/ISAT_with_segment_anything/images",
        "name": "54534_25570.png",
        "width": 256,
        "height": 256,
        "depth": 3,
        "note": ""
    },
    "objects": [
        {
            "category": "greenhouse",
            "group": 2,
            "segmentation": [
                [
                    81.69,
                    103.79
                ],
                [
                    89.38,
                    103.37
                ],
                [
                    82.11,
                    231.63
                ],
                [
                    75.53,
                    231.77
                ]
            ],
            "area": 912.0866823500328,
            "layer": 2.0,
            "bbox": [
                75.02055513565026,
                102.86642096411303,
                89.87764019405792,
                232.27903398927327
            ],
            "iscrowd": false,
            "note": ""
        },
        {
            "category": "greenhouse",
            "group": 3,
            "segmentation": [
                [
                    208.1,
                    97.28
                ],
                [
                    214.38,
                    96.84
                ],
                [
                    213.13,
                    221.65
                ],
                [
                    206.79,
                    222.07
                ]
            ],
            "area": 786.5010155310902,
            "layer": 3.0,
            "bbox": [
                206.2575944691024,
                96.34594362837372,
                214.87834120388672,
                222.60115192481308
            ],
            "iscrowd": false,
            "note": ""
        },
        {
            "category": "greenhouse",
            "group": 3,
            "segmentation": [
                [
                    173.14,
                    102.1
                ],
                [
                    179.94,
                    101.36
                ],
                [
                    177.22,
                    223.26
                ],
                [
                    170.99,
                    223.59
                ]
            ],
            "area": 791.2683951026775,
            "layer": 3.0,
            "bbox": [
                170.46720467092499,
                100.85968937113554,
                180.44119873397221,
                224.11721704425983
            ],
            "iscrowd": false,
            "note": ""
        },
        {
            "category": "greenhouse",
            "group": 3,
            "segmentation": [
                [
                    152.69,
                    102.08
                ],
                [
                    158.33,
                    101.45
                ],
                [
                    155.9,
                    224.04
                ],
                [
                    150.18,
                    224.21
                ]
            ],
            "area": 693.8090093207829,
            "layer": 3.0,
            "bbox": [
                149.66595044501017,
                100.95303960778378,
                158.83094468631543,
                224.72090155254196
            ],
            "iscrowd": false,
            "note": ""
        },
        {
            "category": "greenhouse",
            "group": 3,
            "segmentation": [
                [
                    132.69,
                    102.24
                ],
                [
                    140.43,
                    101.03
                ],
                [
                    136.32,
                    226.47
                ],
                [
                    128.58,
                    226.47
                ]
            ],
            "area": 963.060222143673,
            "layer": 3.0,
            "bbox": [
                128.08410700236033,
                100.53636377069328,
                140.9271120039832,
                226.97238394964592
            ],
            "iscrowd": false,
            "note": ""
        },
        {
            "category": "greenhouse",
            "group": 4,
            "segmentation": [
                [
                    171.41,
                    23.77
                ],
                [
                    177.45,
                    23.77
                ],
                [
                    176.24,
                    86.81
                ],
                [
                    169.79,
                    86.0
                ]
            ],
            "area": 391.6887586733292,
            "layer": 7.0,
            "bbox": [
                169.23570679426987,
                23.267112509834774,
                177.9475871524349,
                87.30652446156691
            ],
            "iscrowd": false,
            "note": ""
        },
        {
            "category": "greenhouse",
            "group": 5,
            "segmentation": [
                [
                    51.72,
                    240.01
                ],
                [
                    89.67,
                    237.35
                ],
                [
                    87.74,
                    255.0
                ],
                [
                    51.72,
                    255.0
                ]
            ],
            "area": 602.2949841684112,
            "layer": 8.0,
            "bbox": [
                51.189958692359895,
                236.85008189644606,
                90.16752237504166,
                255.5
            ],
            "iscrowd": false,
            "note": ""
        },
        {
            "category": "greenhouse",
            "group": 6,
            "segmentation": [
                [
                    93.54,
                    239.04
                ],
                [
                    100.31,
                    238.07
                ],
                [
                    99.58,
                    255.0
                ],
                [
                    92.33,
                    255.0
                ]
            ],
            "area": 114.7838100927238,
            "layer": 9.0,
            "bbox": [
                91.82918961447677,
                237.57898276693805,
                100.80481327078475,
                255.5
            ],
            "iscrowd": false,
            "note": ""
        },
        {
            "category": "greenhouse",
            "group": 7,
            "segmentation": [
                [
                    117.95,
                    247.26
                ],
                [
                    128.83,
                    246.78
                ],
                [
                    129.07,
                    255.0
                ],
                [
                    117.22,
                    255.0
                ]
            ],
            "area": 90.6293065484897,
            "layer": 10.0,
            "bbox": [
                116.72423288749015,
                246.2756307836276,
                129.56729014983028,
                255.5
            ],
            "iscrowd": false,
            "note": ""
        },
        {
            "category": "greenhouse",
            "group": 8,
            "segmentation": [
                [
                    168.22,
                    233.24
                ],
                [
                    186.59,
                    231.06
                ],
                [
                    186.59,
                    255.0
                ],
                [
                    168.22,
                    255.0
                ]
            ],
            "area": 419.69262862587493,
            "layer": 11.0,
            "bbox": [
                167.66748644641447,
                230.56814292384738,
                187.091974822974,
                255.5
            ],
            "iscrowd": false,
            "note": ""
        },
        {
            "category": "greenhouse",
            "group": 9,
            "segmentation": [
                [
                    226.87,
                    156.8
                ],
                [
                    233.31,
                    156.66
                ],
                [
                    233.0,
                    220.43
                ],
                [
                    242.42,
                    220.91
                ],
                [
                    241.46,
                    158.8
                ],
                [
                    248.23,
                    158.55
                ],
                [
                    248.23,
                    220.43
                ],
                [
                    255.0,
                    219.7
                ],
                [
                    255.0,
                    91.36
                ],
                [
                    220.43,
                    91.85
                ],
                [
                    220.43,
                    219.95
                ],
                [
                    227.44,
                    219.7
                ],
                [
                    227.2,
                    161.94
                ]
            ],
            "area": 3687.687305213707,
            "layer": 1.0,
            "bbox": [
                219.929897718332,
                90.86244069241481,
                255.5,
                221.41264044857536
            ],
            "iscrowd": false,
            "note": ""
        },
        {
            "category": "greenhouse",
            "group": 10,
            "segmentation": [
                [
                    246.53,
                    85.27
                ],
                [
                    255.0,
                    84.98
                ],
                [
                    255.0,
                    0.0
                ],
                [
                    243.05,
                    0.0
                ]
            ],
            "area": 869.1218109076144,
            "layer": 12.0,
            "bbox": [
                242.5529661683713,
                -0.5,
                255.5,
                85.78839104604029
            ],
            "iscrowd": false,
            "note": ""
        }
    ]
}