{
    "info": {
        "description": "ISAT",
        "folder": "D:/expermients/Dr_code/zxp_other/ISAT_with_segment_anything/images",
        "name": "54547_25587.png",
        "width": 256,
        "height": 256,
        "depth": 3,
        "note": ""
    },
    "objects": [
        {
            "category": "greenhouse",
            "group": 1,
            "segmentation": [
                [
                    76.57,
                    96.41
                ],
                [
                    84.92,
                    96.41
                ],
                [
                    85.27,
                    222.05
                ],
                [
                    78.66,
                    222.4
                ]
            ],
            "area": 941.3096999999998,
            "layer": 1.0,
            "bbox": [
                76.07,
                95.91,
                85.7699980599286,
                222.9257385443475
            ],
            "iscrowd": false,
            "note": ""
        },
        {
            "category": "greenhouse",
            "group": 2,
            "segmentation": [
                [
                    123.9,
                    226.93
                ],
                [
                    130.87,
                    225.88
                ],
                [
                    132.26,
                    255.0
                ],
                [
                    125.65,
                    255.0
                ]
            ],
            "area": 194.98429999999826,
            "layer": 2.0,
            "bbox": [
                123.33109635225802,
                225.3855787500297,
                132.75943134941463,
                255.5
            ],
            "iscrowd": false,
            "note": ""
        },
        {
            "category": "greenhouse",
            "group": 3,
            "segmentation": [
                [
                    87.71,
                    230.76
                ],
                [
                    93.97,
                    230.76
                ],
                [
                    92.93,
                    255.0
                ],
                [
                    87.71,
                    255.0
                ]
            ],
            "area": 139.13760000000002,
            "layer": 3.0,
            "bbox": [
                87.21,
                230.26,
                94.4695404398297,
                255.5
            ],
            "iscrowd": false,
            "note": ""
        },
        {
            "category": "greenhouse",
            "group": 4,
            "segmentation": [
                [
                    141.45,
                    64.56
                ],
                [
                    187.18,
                    61.91
                ],
                [
                    187.98,
                    72.17
                ],
                [
                    142.21,
                    74.07
                ]
            ],
            "area": 454.01324999999906,
            "layer": 4.0,
            "bbox": [
                140.9219115200459,
                61.41083740826167,
                188.47848695982847,
                74.59030783941218
            ],
            "iscrowd": false,
            "note": ""
        },
        {
            "category": "greenhouse",
            "group": 4,
            "segmentation": [
                [
                    139.76,
                    51.03
                ],
                [
                    185.49,
                    48.38
                ],
                [
                    186.29,
                    58.64
                ],
                [
                    140.51,
                    60.53
                ]
            ],
            "area": 453.81865000000016,
            "layer": 4.0,
            "bbox": [
                139.2319115200459,
                47.88083740826167,
                186.78848695982848,
                61.05019907640089
            ],
            "iscrowd": false,
            "note": ""
        },
        {
            "category": "greenhouse",
            "group": 4,
            "segmentation": [
                [
                    138.55,
                    37.01
                ],
                [
                    184.28,
                    34.36
                ],
                [
                    184.84,
                    43.65
                ],
                [
                    139.31,
                    46.51
                ]
            ],
            "area": 430.5121500000005,
            "layer": 4.0,
            "bbox": [
                138.02191152004593,
                33.860837408261666,
                185.33909405247783,
                47.04036253676056
            ],
            "iscrowd": false,
            "note": ""
        },
        {
            "category": "greenhouse",
            "group": 4,
            "segmentation": [
                [
                    137.58,
                    24.2
                ],
                [
                    183.31,
                    21.55
                ],
                [
                    183.88,
                    30.84
                ],
                [
                    138.34,
                    33.7
                ]
            ],
            "area": 430.57289999999966,
            "layer": 4.0,
            "bbox": [
                137.05191152004593,
                21.050837408261668,
                184.37906150017596,
                34.230356111234336
            ],
            "iscrowd": false,
            "note": ""
        },
        {
            "category": "greenhouse",
            "group": 5,
            "segmentation": [
                [
                    138.74,
                    10.39
                ],
                [
                    183.69,
                    7.98
                ],
                [
                    182.48,
                    0.0
                ],
                [
                    138.25,
                    0.0
                ]
            ],
            "area": 410.5834,
            "layer": 8.0,
            "bbox": [
                137.75,
                -0.5,
                184.18434940768063,
                10.916052016727038
            ],
            "iscrowd": false,
            "note": ""
        },
        {
            "category": "greenhouse",
            "group": 6,
            "segmentation": [
                [
                    225.61,
                    57.77
                ],
                [
                    226.19,
                    67.27
                ],
                [
                    255.0,
                    65.26
                ],
                [
                    255.0,
                    54.87
                ],
                [
                    255.0,
                    56.32
                ]
            ],
            "area": 268.8037000000004,
            "layer": 9.0,
            "bbox": [
                225.0804596768698,
                54.87,
                255.5,
                67.76878755041811
            ],
            "iscrowd": false,
            "note": ""
        },
        {
            "category": "greenhouse",
            "group": 7,
            "segmentation": [
                [
                    224.78,
                    45.44
                ],
                [
                    225.51,
                    53.66
                ],
                [
                    255.0,
                    51.24
                ],
                [
                    255.0,
                    42.78
                ]
            ],
            "area": 249.91780000000108,
            "layer": 10.0,
            "bbox": [
                224.237730299847,
                42.28,
                255.5,
                54.158324924094956
            ],
            "iscrowd": false,
            "note": ""
        },
        {
            "category": "greenhouse",
            "group": 8,
            "segmentation": [
                [
                    224.65,
                    33.09
                ],
                [
                    255.0,
                    30.1
                ],
                [
                    255.0,
                    39.72
                ],
                [
                    224.88,
                    41.65
                ]
            ],
            "area": 275.11905000000024,
            "layer": 11.0,
            "bbox": [
                224.1033875623057,
                29.60240889370059,
                255.5,
                42.18094962539229
            ],
            "iscrowd": false,
            "note": ""
        },
        {
            "category": "greenhouse",
            "group": 8,
            "segmentation": [
                [
                    224.48,
                    31.74
                ],
                [
                    255.0,
                    30.1
                ],
                [
                    255.0,
                    39.72
                ],
                [
                    224.88,
                    41.65
                ]
            ],
            "area": 296.43180000000075,
            "layer": 11.0,
            "bbox": [
                223.95389138813943,
                29.60072030988856,
                255.5,
                42.18094962539229
            ],
            "iscrowd": false,
            "note": ""
        },
        {
            "category": "greenhouse",
            "group": 8,
            "segmentation": [
                [
                    223.88,
                    19.26
                ],
                [
                    254.8,
                    17.61
                ],
                [
                    254.8,
                    27.23
                ],
                [
                    224.27,
                    29.17
                ]
            ],
            "area": 300.3796500000003,
            "layer": 11.0,
            "bbox": [
                223.35406654944148,
                17.110710399408376,
                255.3,
                29.700701660883645
            ],
            "iscrowd": false,
            "note": ""
        },
        {
            "category": "greenhouse",
            "group": 9,
            "segmentation": [
                [
                    222.12,
                    13.54
                ],
                [
                    255.0,
                    12.81
                ],
                [
                    255.0,
                    2.66
                ],
                [
                    221.88,
                    3.14
                ]
            ],
            "area": 339.1475999999998,
            "layer": 14.0,
            "bbox": [
                221.37280688578915,
                2.1600525017064505,
                255.5,
                14.05097505219813
            ],
            "iscrowd": false,
            "note": ""
        }
    ]
}